TNSA/__init__.py
TNSA/tnsaltk.py
TNSALTK/__init__.py
TNSALTK/tnsaltk.py
TNSALTK-0.1.3.dist-info/METADATA
TNSALTK-0.1.3.dist-info/WHEEL
TNSALTK-0.1.3.dist-info/top_level.txt
TNSALTK-0.1.3.dist-info/RECORD
