Metadata-Version: 2.1
Name: TNSALTK
Version: 0.1.3
Summary: TNSALTK is a module by TNSA which is use in development of LLM
Home-page: UNKNOWN
Author: TNSA
Author-email: thishyakethabimalla@gmail.com
License: UNKNOWN
Platform: UNKNOWN
